README.rst
setup.cfg
setup.py
transmogrify.xmlsource.egg-info/PKG-INFO
transmogrify.xmlsource.egg-info/SOURCES.txt
transmogrify.xmlsource.egg-info/dependency_links.txt
transmogrify.xmlsource.egg-info/entry_points.txt
transmogrify.xmlsource.egg-info/not-zip-safe
transmogrify.xmlsource.egg-info/requires.txt
transmogrify.xmlsource.egg-info/top_level.txt
transmogrifyxmlsource/__init__.py
transmogrifyxmlsource/configure.zcml