Metadata-Version: 1.0
Name: transmogrify.xmlsource
Version: 1.0
Summary: Simple xml reader for a transmogrifier pipeline
Home-page: UNKNOWN
Author: UNKNOWN
Author-email: UNKNOWN
License: UNKNOWN
Platform: UNKNOWN
